FormulatedAutomation/__init__.py
FormulatedAutomation/version.py
FormulatedAutomation/Profiler/DebugKeywords.py
FormulatedAutomation/Profiler/__init__.py
FormulatedAutomation/Profiler/system_base.py
FormulatedAutomation/Profiler/system_darwin.py
FormulatedAutomation/Profiler/system_linux.py
FormulatedAutomation/Profiler/system_win.py
FormulatedAutomation/Profiler/utils.py
fa_profiler-0.1.3.dist-info/LICENSE
fa_profiler-0.1.3.dist-info/METADATA
fa_profiler-0.1.3.dist-info/WHEEL
fa_profiler-0.1.3.dist-info/top_level.txt
fa_profiler-0.1.3.dist-info/RECORD
