Metadata-Version: 2.1
Name: fa-profiler
Version: 0.1.3
Summary: Robot Framework System Profiler
Home-page: https://github.com/FormulatedAutomation/Profiler
Author: Formulated Automation
Author-email: hello@formulatedautomation.com
License: Apache License 2.0
Keywords: robotframework testing testautomation profiler
Platform: any
Classifier: Development Status :: 5 - Production/Stable
Classifier: License :: OSI Approved :: Apache Software License
Classifier: Operating System :: OS Independent
Classifier: Programming Language :: Python
Classifier: Programming Language :: Python :: 2.7
Classifier: Programming Language :: Python :: 3.8
Classifier: Topic :: Software Development :: Testing
Classifier: Framework :: Robot Framework
Classifier: Framework :: Robot Framework :: Library
Requires-Dist: robotframework (>=3.0)
Requires-Dist: pyyaml (>=5.3.1)
